README.rst
setup.py
bin/rss2jira
rss2jira/__init__.py
rss2jira/app.py
rss2jira/binding.py
rss2jira/issueFactory.py
rss2jira/rssreader.py
rss2jira/trackedentries.py
rss2jira.egg-info/PKG-INFO
rss2jira.egg-info/SOURCES.txt
rss2jira.egg-info/dependency_links.txt
rss2jira.egg-info/requires.txt
rss2jira.egg-info/top_level.txt
test/testhelpers.py