Metadata-Version: 1.1
Name: rss2jira
Version: 0.1.20
Summary: Create JIRA issues from RSS entries matching key terms.
Home-page: https://github.com/nnutter/rss2jira
Author: nnutter
Author-email: iam@nnutter.com
License: BSD
Keywords: rss,jira,rss2jira
Platform: UNKNOWN
Classifier: Development Status :: 2 - Pre-Alpha
Classifier: Environment :: Console
Classifier: Intended Audience :: Developers
Classifier: License :: OSI Approved :: BSD License
Classifier: Operating System :: OS Independent
Classifier: Programming Language :: Python :: 2.7
Classifier: Topic :: Software Development :: Bug Tracking
